liblibftk.dylib
pyftk.cpython-39-darwin.so
pyftk-0.0.7.1.dist-info/LICENSE.txt
pyftk-0.0.7.1.dist-info/METADATA
pyftk-0.0.7.1.dist-info/WHEEL
pyftk-0.0.7.1.dist-info/top_level.txt
pyftk-0.0.7.1.dist-info/RECORD
