Metadata-Version: 2.1
Name: pyftk
Version: 0.0.7.1
Summary: FTK: A Feature Tracking Kit
Home-page: https://github.com/hguo/ftk
Author: Hanqi Guo
Author-email: guohanqi@gmail.com
License: MIT
Platform: UNKNOWN
License-File: LICENSE.txt
Requires-Dist: numpy
